slackattack/__init__.py
slackattack/_version.py
slackattack/slackattack.py
slackattack-1.2.4.dist-info/LICENSE
slackattack-1.2.4.dist-info/METADATA
slackattack-1.2.4.dist-info/WHEEL
slackattack-1.2.4.dist-info/entry_points.txt
slackattack-1.2.4.dist-info/top_level.txt
slackattack-1.2.4.dist-info/RECORD
