Metadata-Version: 2.1
Name: slackattack
Version: 1.2.4
Summary: Slack post-exploitation script for leaked bot tokens and "d" cookies
Home-page: https://github.com/fr4nk3nst1ner/slackattack
Author: Jonathan Stines
License: UNKNOWN
Platform: UNKNOWN
Classifier: Programming Language :: Python :: 3
Classifier: License :: OSI Approved :: MIT License
Classifier: Operating System :: OS Independent
License-File: LICENSE
Requires-Dist: argparse
Requires-Dist: requests
Requires-Dist: datetime
Requires-Dist: termcolor
Requires-Dist: colorama
